qe_rho/__init__.py
qe_rho/heapsort.py
qe_rho/meshplot.py
qe_rho/superpos_atom_rho.py
qe_rho/upf_reader.py
qe_rho/utils.py
qe_rho-1.0.6.dist-info/LICENSE
qe_rho-1.0.6.dist-info/METADATA
qe_rho-1.0.6.dist-info/WHEEL
qe_rho-1.0.6.dist-info/top_level.txt
qe_rho-1.0.6.dist-info/RECORD
