Metadata-Version: 2.1
Name: qe-rho
Version: 1.0.6
Summary: A package to generate charge-density.dat for Quantum ESPRESSO
Home-page: https://github.com/ziangziangziang/pyQErho
Author: Ziang
Author-email: ziang.zhang@kaust.edu.sa
License: UNKNOWN
Project-URL: Bug Tracker, https://github.com/pypa/sampleproject/issues
Platform: UNKNOWN
Classifier: Programming Language :: Python :: 3
Classifier: License :: OSI Approved :: MIT License
Classifier: Operating System :: OS Independent
Requires-Python: >=3.6
License-File: LICENSE
